kio/__init__.py
kio/pipeline_operations.py
kio/py.typed
kio_dataprocessing-0.1.0.dist-info/licenses/LICENSE
kio_dataprocessing-0.1.0.dist-info/METADATA
kio_dataprocessing-0.1.0.dist-info/WHEEL
kio_dataprocessing-0.1.0.dist-info/top_level.txt
kio_dataprocessing-0.1.0.dist-info/RECORD
